Metadata-Version: 1.0
Name: clipsync
Version: 0.2
Summary: cli for zeroconf shared clipboards over local networks
Home-page: https://www.github.com/illberoy/clipsync
Author: Roy Sommer
Author-email: UNKNOWN
License: UNKNOWN
Platform: UNKNOWN
